{
  "body": [
    null,
    {
      "expression": {
        "arguments": [
          null,
          {
            "body": {
              "body": [
                null,
                null,
                {
                  "body": {
                    "body": [
                      {
                        "body": [
                          null,
                          {
                            "body": [
                              null,
                              null,
                              null,
                              null,
                              null,
                              null,
                              {
                                "consequent": {
                                  "body": [
                                    {
                                      "body": [
                                        null,
                                        null,
                                        {
                                          "body": {
                                            "body": [
                                              null,
                                              {
                                                "test": {
                                                  "right": {
                                                    "type": "MemberExpression"
                                                  },
                                                  "type": "BinaryExpression"
                                                },
                                                "type": "ForStatement",
                                                "update": {
                                                  "argument": {
                                                    "name": "colNum",
                                                    "type": "Identifier"
                                                  },
                                                  "operator": "++",
                                                  "prefix": false,
                                                  "type": "UpdateExpression"
                                                }
                                              }
                                            ],
                                            "type": "BlockStatement"
                                          },
                                          "init": {
                                            "left": {
                                              "name": "rowNum",
                                              "type": "Identifier"
                                            },
                                            "operator": "=",
                                            "right": {
                                              "raw": "0",
                                              "type": "Literal",
                                              "value": 0
                                            },
                                            "type": "AssignmentExpression"
                                          },
                                          "test": {
                                            "left": {
                                              "name": "rowNum",
                                              "type": "Identifier"
                                            },
                                            "operator": "<",
                                            "right": {
                                              "computed": false,
                                              "object": {
                                                "name": "dungeonConfig",
                                                "type": "Identifier"
                                              },
                                              "property": {
                                                "name": "n_i",
                                                "type": "Identifier"
                                              }
                                            }
                                          }
                                        }
                                      ]
                                    }
                                  ]
                                }
                              }
                            ]
                          }
                        ]
                      }
                    ]
                  }
                }
              ]
            }
          }
        ]
      }
    }
  ]
}
